pathroot.py
pathroot-1.0.0.dist-info/METADATA
pathroot-1.0.0.dist-info/WHEEL
pathroot-1.0.0.dist-info/top_level.txt
pathroot-1.0.0.dist-info/RECORD
