Metadata-Version: 2.4
Name: pathroot
Version: 1.0.0
Summary: Subclass of a pathlib.Path object that does not allow traversal outside of a trusted root.
Author-email: Josh Schneider <josh.schneider@gmail.com>
Maintainer-email: Josh Schneider <josh.schneider@gmail.com>
License-Expression: MIT
Keywords: path,pathlib,filesystem
Requires-Python: >=3.10
Provides-Extra: dev
Requires-Dist: ruff; extra == "dev"
Requires-Dist: pytest; extra == "dev"
